odoo/addons/pos_partner_ref/README.rst
odoo/addons/pos_partner_ref/__init__.py
odoo/addons/pos_partner_ref/__manifest__.py
odoo/addons/pos_partner_ref/i18n/es.po
odoo/addons/pos_partner_ref/i18n/fr.po
odoo/addons/pos_partner_ref/i18n/it.po
odoo/addons/pos_partner_ref/i18n/pos_partner_ref.pot
odoo/addons/pos_partner_ref/models/__init__.py
odoo/addons/pos_partner_ref/models/pos_session.py
odoo/addons/pos_partner_ref/readme/CONTRIBUTORS.md
odoo/addons/pos_partner_ref/readme/DESCRIPTION.md
odoo/addons/pos_partner_ref/readme/newsfragments/.gitkeep
odoo/addons/pos_partner_ref/static/description/icon.png
odoo/addons/pos_partner_ref/static/description/index.html
odoo/addons/pos_partner_ref/static/src/js/ClientDetailsEdit.esm.js
odoo/addons/pos_partner_ref/static/src/js/PosDB.esm.js
odoo/addons/pos_partner_ref/static/src/xml/screens.xml
odoo_addon_pos_partner_ref-17.0.1.0.0.10.dist-info/METADATA
odoo_addon_pos_partner_ref-17.0.1.0.0.10.dist-info/WHEEL
odoo_addon_pos_partner_ref-17.0.1.0.0.10.dist-info/top_level.txt
odoo_addon_pos_partner_ref-17.0.1.0.0.10.dist-info/RECORD
